weiche/__init__.py
weiche/const.py
weiche/formatter.py
weiche/objects.py
weiche/schiene.py
weiche/version.py
weiche/api/__init__.py
weiche/api/asynchronous.py
weiche/api/base.py
weiche/api/parser.py
weiche/api/synchronous.py
weiche/tests/__init__.py
weiche/tests/test_asynchronous.py
weiche/tests/test_schiene.py
weiche/tests/test_synchronous.py
weiche-0.10.1.dist-info/licenses/LICENSE
weiche-0.10.1.dist-info/METADATA
weiche-0.10.1.dist-info/WHEEL
weiche-0.10.1.dist-info/top_level.txt
weiche-0.10.1.dist-info/RECORD
