Metadata-Version: 2.4
Name: weiche
Version: 0.10.1
Summary: A wrapper around the DB Website API for querying train connections.
Author-email: Christoph Brand <christoph+pypi@brand.rest>
License: MIT License
Project-URL: Homepage, https://github.com/cbrand/weiche
Classifier: Development Status :: 3 - Alpha
Classifier: Intended Audience :: Developers
Classifier: License :: OSI Approved :: MIT No Attribution License (MIT-0)
Classifier: Programming Language :: Python
Classifier: Programming Language :: Python :: 3
Classifier: Programming Language :: Python :: 3.10
Classifier: Programming Language :: Python :: 3.11
Classifier: Programming Language :: Python :: 3.12
Classifier: Programming Language :: Python :: 3.13
Classifier: Programming Language :: Python :: Implementation :: CPython
Requires-Python: >=3.10
License-File: LICENSE
Requires-Dist: pydantic<3,>=2
Provides-Extra: test
Requires-Dist: pytest; extra == "test"
Requires-Dist: pytest-asyncio; extra == "test"
Requires-Dist: tox; extra == "test"
Requires-Dist: requests; extra == "test"
Requires-Dist: aiohttp; extra == "test"
Provides-Extra: sync
Requires-Dist: requests; extra == "sync"
Provides-Extra: async
Requires-Dist: aiohttp; extra == "async"
Provides-Extra: schiene
Requires-Dist: requests; extra == "schiene"
Dynamic: license-file
